rainreader/__init__.py
rainreader/rainreader.py
rainreader-1.1.0.dist-info/METADATA
rainreader-1.1.0.dist-info/RECORD
rainreader-1.1.0.dist-info/WHEEL
rainreader-1.1.0.dist-info/top_level.txt
