Metadata-Version: 2.1
Name: rainreader
Version: 1.1.0
Summary: Python Package for reading KMD files from The Danish Meterological Institute (DMI) as well as simple simple analysis for the data
Home-page: https://github.com/enielsen93/rainreader
Author: Emil Nielsen
Author-email: enielsen93@hotmail.com
License: BSD 2-clause
Platform: UNKNOWN
Classifier: Development Status :: 1 - Planning
Classifier: Intended Audience :: Science/Research
Classifier: License :: OSI Approved :: BSD License
Classifier: Operating System :: POSIX :: Linux
Classifier: Programming Language :: Python :: 2
Classifier: Programming Language :: Python :: 2.7
Classifier: Programming Language :: Python :: 3
Classifier: Programming Language :: Python :: 3.4
Classifier: Programming Language :: Python :: 3.5
Requires-Dist: numpy
Requires-Dist: matplotlib
